beamlime/__init__.py
beamlime/_nexus_helpers.py
beamlime/_random_data_providers.py
beamlime/fakes.py
beamlime/py.typed
beamlime/service_factory.py
beamlime/sinks.py
beamlime/workflow_protocols.py
beamlime/config/__init__.py
beamlime/config/config_loader.py
beamlime/config/config_names.py
beamlime/config/env.py
beamlime/config/models.py
beamlime/config/streams.py
beamlime/config/defaults/control_consumer.yaml
beamlime/config/defaults/kafka_downstream_dev.yaml
beamlime/config/defaults/kafka_downstream_docker.yaml.jinja
beamlime/config/defaults/kafka_upstream_dev.yaml
beamlime/config/defaults/kafka_upstream_docker.yaml.jinja
beamlime/config/defaults/raw_data_consumer.yaml
beamlime/config/defaults/reduced_data_consumer.yaml
beamlime/config/instruments/__init__.py
beamlime/config/instruments/_ess.py
beamlime/config/instruments/bifrost.py
beamlime/config/instruments/dream.py
beamlime/config/instruments/dummy.py
beamlime/config/instruments/loki.py
beamlime/config/instruments/nmx.py
beamlime/config/instruments/odin.py
beamlime/config/instruments/tbl.py
beamlime/core/__init__.py
beamlime/core/config_service.py
beamlime/core/handler.py
beamlime/core/message.py
beamlime/core/processor.py
beamlime/core/service.py
beamlime/handlers/__init__.py
beamlime/handlers/accumulators.py
beamlime/handlers/config_handler.py
beamlime/handlers/data_reduction_handler.py
beamlime/handlers/detector_data_handler.py
beamlime/handlers/monitor_data_handler.py
beamlime/handlers/timeseries_handler.py
beamlime/handlers/to_nx_log.py
beamlime/handlers/workflow_manager.py
beamlime/kafka/__init__.py
beamlime/kafka/consumer.py
beamlime/kafka/message_adapter.py
beamlime/kafka/routes.py
beamlime/kafka/scipp_da00_compat.py
beamlime/kafka/sink.py
beamlime/kafka/source.py
beamlime/kafka/stream_mapping.py
beamlime/services/dashboard.py
beamlime/services/data_reduction.py
beamlime/services/detector_data.py
beamlime/services/fake_detectors.py
beamlime/services/fake_logdata.py
beamlime/services/fake_monitors.py
beamlime-25.4.0.dist-info/licenses/LICENSE
beamlime-25.4.0.dist-info/METADATA
beamlime-25.4.0.dist-info/WHEEL
beamlime-25.4.0.dist-info/entry_points.txt
beamlime-25.4.0.dist-info/top_level.txt
beamlime-25.4.0.dist-info/RECORD
