Metadata-Version: 2.4
Name: beamlime
Version: 25.4.0
Summary: Live data reduction visualisation framework for ESS.
Author: Scipp contributors
License: BSD 3-Clause License
Project-URL: Bug Tracker, https://github.com/scipp/beamlime/issues
Project-URL: Documentation, https://scipp.github.io/beamlime
Project-URL: Source, https://github.com/scipp/beamlime
Classifier: Intended Audience :: Science/Research
Classifier: License :: OSI Approved :: BSD License
Classifier: Natural Language :: English
Classifier: Operating System :: OS Independent
Classifier: Programming Language :: Python :: 3
Classifier: Programming Language :: Python :: 3 :: Only
Classifier: Programming Language :: Python :: 3.10
Classifier: Programming Language :: Python :: 3.11
Classifier: Programming Language :: Python :: 3.12
Classifier: Programming Language :: Python :: 3.13
Classifier: Topic :: Scientific/Engineering
Classifier: Typing :: Typed
Requires-Python: >=3.10
License-File: LICENSE
Requires-Dist: PyYAML
Requires-Dist: confluent_kafka
Requires-Dist: ess-streaming-data-types
Requires-Dist: essreduce>=25.03.1
Requires-Dist: jinja2
Requires-Dist: pydantic>=2
Requires-Dist: scipp>=25.02.0
Requires-Dist: pooch
Provides-Extra: test
Requires-Dist: esssans; extra == "test"
Requires-Dist: essspectroscopy; extra == "test"
Requires-Dist: pytest; extra == "test"
Requires-Dist: pytest-benchmark; extra == "test"
Provides-Extra: bifrost
Requires-Dist: essspectroscopy; extra == "bifrost"
Provides-Extra: loki
Requires-Dist: esssans; extra == "loki"
Provides-Extra: dashboard
Requires-Dist: dash; extra == "dashboard"
Requires-Dist: gunicorn; extra == "dashboard"
Requires-Dist: plotly; extra == "dashboard"
Dynamic: license-file
